mambavision/__init__.py
mambavision/dummy_test.py
mambavision/tensorboard.py
mambavision/throughput_measure.py
mambavision/train.py
mambavision/validate.py
mambavision/validate_pip_model.py
mambavision/models/__init__.py
mambavision/models/mamba_vision.py
mambavision/models/registry.py
mambavision/scheduler/__init__.py
mambavision/scheduler/cosine_lr.py
mambavision/scheduler/multistep_lr.py
mambavision/scheduler/plateau_lr.py
mambavision/scheduler/poly_lr.py
mambavision/scheduler/scheduler.py
mambavision/scheduler/scheduler_factory.py
mambavision/scheduler/step_lr.py
mambavision/scheduler/tanh_lr.py
mambavision/utils/__init__.py
mambavision/utils/datasets.py
mambavision-1.2.0.dist-info/LICENSE
mambavision-1.2.0.dist-info/METADATA
mambavision-1.2.0.dist-info/WHEEL
mambavision-1.2.0.dist-info/top_level.txt
mambavision-1.2.0.dist-info/RECORD
