Metadata-Version: 2.1
Name: mambavision
Version: 1.2.0
Summary: MambaVision: A Hybrid Mamba-Transformer Vision Backbone
Home-page: https://github.com/NVlabs/MambaVision
Author: Ali Hatamizadeh
Author-email: ahatamiz123@gmail.com
License: NVIDIA Source Code License-NC
Keywords: pytorch pretrained models mamba vision transformer vit
Classifier: Programming Language :: Python :: 3.7
Classifier: Programming Language :: Python :: 3.8
Classifier: Programming Language :: Python :: 3.9
Classifier: Programming Language :: Python :: 3.10
Classifier: Programming Language :: Python :: 3.11
Classifier: Programming Language :: Python :: 3.12
Classifier: Programming Language :: Python :: 3.13
Classifier: Topic :: Scientific/Engineering :: Artificial Intelligence
Classifier: Topic :: Software Development
Classifier: Topic :: Software Development :: Libraries
Classifier: Topic :: Software Development :: Libraries :: Python Modules
Requires-Python: >=3.9
License-File: LICENSE
Requires-Dist: timm ==1.0.15
Requires-Dist: transformers ==4.50.0
Requires-Dist: mamba-ssm ==2.2.4
Requires-Dist: einops ==0.8.1
Requires-Dist: requests ==2.32.3
Requires-Dist: Pillow ==11.1.0
